magpurify2-1.0.2.dist-info/top_level.txt
magpurify2-1.0.2.dist-info/LICENSE
magpurify2-1.0.2.dist-info/RECORD
magpurify2-1.0.2.dist-info/METADATA
magpurify2-1.0.2.dist-info/WHEEL
magpurify2-1.0.2.dist-info/entry_points.txt
magpurify2.libs/liblzma-004595ca.so.5.2.2
magpurify2/_codon.cpython-38-x86_64-linux-gnu.so
magpurify2/_mmseqs2.cpython-38-x86_64-linux-gnu.so
magpurify2/_composition.cpython-38-x86_64-linux-gnu.so
magpurify2/external.py
magpurify2/core.py
magpurify2/tools.py
magpurify2/cli.py
magpurify2/_coverage.cpython-38-x86_64-linux-gnu.so
magpurify2/__init__.py
magpurify2/models/full_model.json
magpurify2/models/fast_model.json
magpurify2/modules/coverage.py
magpurify2/modules/filter.py
magpurify2/modules/codon_usage.py
magpurify2/modules/end_to_end.py
magpurify2/modules/composition.py
magpurify2/modules/taxonomy.py
magpurify2/modules/__init__.py
