Metadata-Version: 2.1
Name: magpurify2
Version: 1.0.2
Summary: Identify and remove contaminants from metagenome-assembled genomes.
Home-page: https://github.com/apcamargo/magpurify2/
Author: Antonio Camargo
Author-email: antoniop.camargo@gmail.com
License: GNU General Public License v3.0
Keywords: bioinformatics,metagenomics,metagenome-assembled genomes
Classifier: Intended Audience :: Science/Research
Classifier: Natural Language :: English
Classifier: Topic :: Software Development :: Libraries
Classifier: Topic :: Scientific/Engineering :: Bio-Informatics
Classifier: License :: OSI Approved :: GNU General Public License (GPL)
Classifier: Programming Language :: Python :: 3
Requires-Python: >=3.6
License-File: LICENSE
Requires-Dist: biolib
Requires-Dist: biopython
Requires-Dist: hdbscan
Requires-Dist: joblib
Requires-Dist: numpy (<1.24)
Requires-Dist: scipy
Requires-Dist: taxopy
Requires-Dist: umap-learn
Requires-Dist: xgboost (<1.6)
Requires-Dist: importlib-metadata (>=0.12) ; python_version < "3.8"
